MDsrv-0.3.5.post1.dist-info/DESCRIPTION.rst
MDsrv-0.3.5.post1.dist-info/METADATA
MDsrv-0.3.5.post1.dist-info/RECORD
MDsrv-0.3.5.post1.dist-info/WHEEL
MDsrv-0.3.5.post1.dist-info/entry_points.txt
MDsrv-0.3.5.post1.dist-info/metadata.json
MDsrv-0.3.5.post1.dist-info/top_level.txt
mdsrv/__init__.py
mdsrv/_version.py
mdsrv/mdsrv.py
mdsrv/trajectory.py
mdsrv/webapp/embedded.html
mdsrv/webapp/favicon.ico
mdsrv/webapp/index.html
mdsrv/webapp/mobile.html
mdsrv/webapp/css/dark.css
mdsrv/webapp/css/font-awesome.min.css
mdsrv/webapp/css/light.css
mdsrv/webapp/css/main.css
mdsrv/webapp/fonts/FontAwesome.otf
mdsrv/webapp/fonts/fontawesome-webfont.eot
mdsrv/webapp/fonts/fontawesome-webfont.svg
mdsrv/webapp/fonts/fontawesome-webfont.ttf
mdsrv/webapp/fonts/fontawesome-webfont.woff
mdsrv/webapp/js/gui.js
mdsrv/webapp/js/ngl.js
mdsrv/webapp/js/lib/colorpicker.min.js
mdsrv/webapp/js/lib/signals.min.js
mdsrv/webapp/js/lib/tether.min.js
mdsrv/webapp/js/ui/ui.extra.js
mdsrv/webapp/js/ui/ui.helper.js
mdsrv/webapp/js/ui/ui.js
mdsrv/webapp/js/ui/ui.ngl.js
