Metadata-Version: 2.0
Name: MDsrv
Version: 0.3.5.post1
Summary: Server for coordinate trajectories from molecular dynamics simulations.
Home-page: https://github.com/arose/mdsrv
Author: Alexander S. Rose, Johanna K. S. Tiemann
Author-email: alexander.rose@weirdbyte.de, johanna.tiemann@gmail.com
License: MIT
Keywords: Molecular Dynamics simulation
Platform: UNKNOWN
Classifier: Development Status :: 3 - Alpha
Classifier: Intended Audience :: Science/Research
Classifier: Intended Audience :: Developers
Classifier: License :: OSI Approved :: MIT License
Classifier: Programming Language :: JavaScript
Classifier: Programming Language :: Python
Classifier: Programming Language :: Python :: 2
Classifier: Programming Language :: Python :: 3
Classifier: Topic :: Scientific/Engineering :: Bio-Informatics
Classifier: Topic :: Scientific/Engineering :: Chemistry
Classifier: Topic :: Scientific/Engineering :: Visualization
Classifier: Operating System :: POSIX
Classifier: Operating System :: Unix
Classifier: Operating System :: MacOS
Requires-Dist: flask
Requires-Dist: mdtraj
